{
  "collectionName": "components_product_variant_informations",
  "info": {
    "displayName": "Variant Information",
    "icon": "apps",
    "description": ""
  },
  "options": {},
  "attributes": {
    "variant_name": {
      "type": "string",
      "required": true
    },
    "variant_price": {
      "type": "decimal",
      "required": true,
      "min": 0
    },
    "length": {
      "type": "integer",
      "required": true,
      "default": 1
    },
    "width": {
      "type": "integer",
      "required": true,
      "default": 1
    },
    "height": {
      "type": "integer",
      "default": 1,
      "required": true
    },
    "weight": {
      "type": "integer",
      "required": true,
      "default": 1
    }
  }
}
